irisvision/__init__.py
irisvision/model.py
irisvision-0.1.0.dist-info/licenses/LICENSE
irisvision-0.1.0.dist-info/METADATA
irisvision-0.1.0.dist-info/WHEEL
irisvision-0.1.0.dist-info/top_level.txt
irisvision-0.1.0.dist-info/RECORD
