Metadata-Version: 2.4
Name: irisvision
Version: 0.1.0
Summary: IrisVision - Face Recognition Suite | Made in Emirates 🇦🇪
Author-email: vCodesUAE <info@vcodes.ae>
Maintainer: Padam Kafle
License: MIT
Project-URL: Homepage, https://github.com/vCodesUAE/irisvision
Project-URL: Documentation, https://github.com/vCodesUAE/irisvision#readme
Project-URL: Repository, https://github.com/vCodesUAE/irisvision
Project-URL: Bug Tracker, https://github.com/vCodesUAE/irisvision/issues
Project-URL: Model Hub, https://huggingface.co/vCodesUAE/IrisVisionAixL
Keywords: face-recognition,computer-vision,deep-learning,arcface,biometrics,pytorch,irisvision,made-in-emirates
Classifier: Development Status :: 4 - Beta
Classifier: Intended Audience :: Developers
Classifier: Intended Audience :: Science/Research
Classifier: License :: OSI Approved :: MIT License
Classifier: Operating System :: OS Independent
Classifier: Programming Language :: Python :: 3
Classifier: Programming Language :: Python :: 3.8
Classifier: Programming Language :: Python :: 3.9
Classifier: Programming Language :: Python :: 3.10
Classifier: Programming Language :: Python :: 3.11
Classifier: Programming Language :: Python :: 3.12
Classifier: Topic :: Scientific/Engineering :: Artificial Intelligence
Classifier: Topic :: Scientific/Engineering :: Image Recognition
Requires-Python: >=3.8
License-File: LICENSE
Requires-Dist: torch>=1.9.0
Requires-Dist: torchvision>=0.10.0
Requires-Dist: huggingface-hub>=0.14.0
Requires-Dist: numpy>=1.19.0
Requires-Dist: Pillow>=8.0.0
Provides-Extra: dev
Requires-Dist: pytest>=6.0; extra == "dev"
Requires-Dist: black; extra == "dev"
Requires-Dist: isort; extra == "dev"
Dynamic: license-file
